archglobe/__init__.py
archglobe/example.py
archglobe-0.0.1.dist-info/METADATA
archglobe-0.0.1.dist-info/WHEEL
archglobe-0.0.1.dist-info/licenses/LICENSE
archglobe-0.0.1.dist-info/RECORD
