Metadata-Version: 2.1
Name: archglobe
Version: 0.0.1
Summary: Web platform for single-cell query to reference mapping
Project-URL: Homepage, https://github.com/pypa/sampleprojec
Project-URL: Bug Tracker, https://github.com/pypa/sampleproject/issues
Author-email: Mohammad Lotfollahi <mohammad.Lotfollahi@helmholtz-muenchen.de>, Malte Luecken <malte.luecken@helmholtz-muenchen.de>, Ronald Skorobogat <ronald.skorobogat@helmholtz-muenchen.de>, Amin Ben Saad <amin.ben-saad@helmholtz-muenchen.de>
License: Copyright (c) 2022 Helmholtz Muenchen
Classifier: License :: OSI Approved :: MIT License
Classifier: Operating System :: OS Independent
Classifier: Programming Language :: Python :: 3
Requires-Python: >=3.7
